NGPIris/__init__.py
NGPIris/cli/__init__.py
NGPIris/cli/helpers.py
NGPIris/cli/sections.py
NGPIris/hci/__init__.py
NGPIris/hci/exceptions.py
NGPIris/hci/hci.py
NGPIris/hci/helpers.py
NGPIris/hcp/__init__.py
NGPIris/hcp/exceptions.py
NGPIris/hcp/hcp.py
NGPIris/hcp/helpers.py
NGPIris/hcp/statistics.py
NGPIris/parse_credentials/__init__.py
NGPIris/parse_credentials/parse_credentials.py
NGPIris/utils/__init__.py
NGPIris/utils/utils.py
ngpiris-5.6.1.dist-info/licenses/LICENSE
ngpiris-5.6.1.dist-info/METADATA
ngpiris-5.6.1.dist-info/WHEEL
ngpiris-5.6.1.dist-info/entry_points.txt
ngpiris-5.6.1.dist-info/top_level.txt
ngpiris-5.6.1.dist-info/RECORD
