Metadata-Version: 2.4
Name: NGPIris
Version: 5.6.1
Author-email: Erik Brink <erik.brink@gu.se>, Isak Sylvin <isak.sylvin@gu.se>
Requires-Python: >=3.11
License-File: LICENSE
Requires-Dist: requests>=2.31.0
Requires-Dist: urllib3==2.6.3
Requires-Dist: boto3==1.35.81
Requires-Dist: parse>=1.19.1
Requires-Dist: RapidFuzz>=3.10.1
Requires-Dist: tqdm>=4.66.2
Requires-Dist: click>=8.1.7
Requires-Dist: bitmath==1.3.3.1
Requires-Dist: lazy_table==0.2.1
Requires-Dist: more-itertools==10.7.0
Requires-Dist: ruff>=0.14.5
Provides-Extra: dev
Requires-Dist: basedpyright>=1.33.0; extra == "dev"
Requires-Dist: ruff>=0.14.5; extra == "dev"
Requires-Dist: pytype>=2024.10.11; extra == "dev"
Requires-Dist: pytest>=8.3.4; extra == "dev"
Requires-Dist: icecream; extra == "dev"
Dynamic: license-file
